{
  "project_info": {
    "project_number": "326100608810",
    "firebase_url": "https://nochancesrealapp-d3a66.firebaseio.com",
    "project_id": "nochancesrealapp-d3a66",
    "storage_bucket": "nochancesrealapp-d3a66.appspot.com"
  },
  "client": [
    {
      "client_info": {
        "mobilesdk_app_id": "1:326100608810:android:ef3147b4312dcf0e",
        "android_client_info": {
          "package_name": "com.example.nochances"
        }
      },
      "oauth_client": [
        {
          "client_id": "326100608810-1m6l742a3vq0fo9rkabvr1uvo2opuiln.apps.googleusercontent.com",
          "client_type": 3
        }
      ],
      "api_key": [
        {
          "current_key": "AIzaSyB9Dl9VBHueKTbJnFCbEzmn3Pxd7pJtviE"
        }
      ],
      "services": {
        "appinvite_service": {
          "other_platform_oauth_client": [
            {
              "client_id": "326100608810-1m6l742a3vq0fo9rkabvr1uvo2opuiln.apps.googleusercontent.com",
              "client_type": 3
            }
          ]
        }
      }
    }
  ],
  "configuration_version": "1"
}